proai/__init__.py
proai/aes.py
proai/cmdline.py
proai/config.py
proai/constants.py
proai/detectors.py
proai/make.py
proai/nocode.py
proai/shelving.py
proai/xml.py
proai/data/__init__.py
proai/data/make_dataset.py
proai/features/__init__.py
proai/features/build_features.py
proai/models/__init__.py
proai/models/predict_model.py
proai/models/train_model.py
proai/visualization/__init__.py
proai/visualization/visualize.py
proai-0.0.8.dist-info/LICENSE
proai-0.0.8.dist-info/METADATA
proai-0.0.8.dist-info/WHEEL
proai-0.0.8.dist-info/top_level.txt
proai-0.0.8.dist-info/RECORD
